MANIFEST.in
README.rst
setup.cfg
setup.py
kotti_feed/__init__.py
kotti_feed/views.py
kotti_feed.egg-info/PKG-INFO
kotti_feed.egg-info/SOURCES.txt
kotti_feed.egg-info/dependency_links.txt
kotti_feed.egg-info/not-zip-safe
kotti_feed.egg-info/requires.txt
kotti_feed.egg-info/top_level.txt
kotti_feed/static/feed-icon-14x14.png
kotti_feed/static/feed-icon-28x28.png
kotti_feed/templates/rss-head-link.pt
kotti_feed/templates/rss-icon.pt